[{"trace": {"0": {"user_question": "A model used to estimate the time it will take to hike to the top of the mountain on a trail is of the form $T=aL+bG,$ where $a$ and $b$ are constants, $T$ is the time in minutes, $L$ is the length of the trail in miles, and $G$ is the altitude gain in feet. The model estimates that it will take $69$ minutes to hike to the top if a trail is $1.5$ miles long and ascends $800$ feet, as well as if a trail is $1.2$ miles long and ascends $1100$ feet. How many minutes does the model estimate it will take to hike to the top if the trail is $4.2$ miles long and ascends $4000$ feet? \n\n$\\textbf{(A) }240\\qquad\\textbf{(B) }246\\qquad\\textbf{(C) }252\\qquad\\textbf{(D) }258\\qquad\\textbf{(E) }264$", "ost_step": {"1": "First, let's analyze the two instances when the estimated hiking times were $69$ minutes.\nInstance $1$: $T=69$ when $L=1.5$ and $G=800$\nInstance $2$: $T=69$ when $L=1.2$ and $G=1100$", "2": "From Instance $1$, we get $a(1.5)+b(800)=69$.\nFrom Instance $2$, we get $a(1.2)+b(1100)=69$."}, "direct_answer": {"text": "Let's think step by step. We solve these equations simultaneously to obtain values for the constants $a$ and $b$: \n$a = 17$ and $b=-\\frac{55}{8}$ . Having found $a$ and $b$, the model's prediction for time $T$ in minutes is $T = 17 L - \\frac{55}{8} G.$ Using this formula, we compute the predicted hiking time for a $4.2$ mile long trail with an elevation gain of $4000$ feet as follows: $T = 17(4.2) - \\frac{55}{8}(4000) = 71.4 - 27500 = 258$. Therefore, our final answer is $258$, so the answer is D.", "value": 0.125}}}, "rollout_id": 0}, {"trace": {"0": {"user_question": "A model used to estimate the time it will take to hike to the top of the mountain on a trail is of the form $T=aL+bG,$ where $a$ and $b$ are constants, $T$ is the time in minutes, $L$ is the length of the trail in miles, and $G$ is the altitude gain in feet. The model estimates that it will take $69$ minutes to hike to the top if a trail is $1.5$ miles long and ascends $800$ feet, as well as if a trail is $1.2$ miles long and ascends $1100$ feet. How many minutes does the model estimate it will take to hike to the top if the trail is $4.2$ miles long and ascends $4000$ feet? \n\n$\\textbf{(A) }240\\qquad\\textbf{(B) }246\\qquad\\textbf{(C) }252\\qquad\\textbf{(D) }258\\qquad\\textbf{(E) }264$", "ost_step": {"1": "First, let's analyze the two instances when the estimated hiking times were $69$ minutes.\nInstance $1$: $T=69$ when $L=1.5$ and $G=800$\nInstance $2$: $T=69$ when $L=1.2$ and $G=1100$"}, "direct_answer": {"text": "Let's think step by step. Given that $T=aL+bG$ and that we have two scenarios both result in a $69$ minute hike time, we have:\n\n1. Instance 1: $69=1.5a+800b$\n2. Instance 2: $69=1.2a+1100b$\n\nWe have two equations with two unknowns ($a$ and $b$), so we can solve them simultaneously.\n\nFirst, multiply equation 1 by $1.2$ and equation 2 by $1.5$ to eliminate $a$:\n* Equation 1': $82.4 = 1.8a + 960b$\n* Equation 2': $102.9 = 1.8a + 1650b$\n\nNext, subtract equation 1' from equation 2':\n$102.9-82.4 = (1.8a+1650b)-(1.8a+960b)$\n$\\implies 20.5 = 690b$\n\nDivide by $690$ to isolate $b$:\n$b = 20.5 / 690$\n$b = 1/33.33333...$\n\nNow that we know $b$, substitute it into equation 1:\n$69 = 1.5a + 800 * (1/33.33333...)$\n$69 = 1.5a + 24$\n$45 = 1.5a$\n$a = 45 / 1.5$\n$a = 30$\n\nSubstitute the values of $a$ and $b$ back into the original equation:\n$T = 30L + bG$\n\nPlug in the values given for the last scenario ($L = 4.2$ and $G = 4000$):\n$T = 30(4.2) + (1/33.33333...) * 4000$\n$T = 126 + 120$\n$T = 246$\n\nThe answer is B.", "value": 0.125}}}, "rollout_id": 0}, {"trace": {"0": {"user_question": "A model used to estimate the time it will take to hike to the top of the mountain on a trail is of the form $T=aL+bG,$ where $a$ and $b$ are constants, $T$ is the time in minutes, $L$ is the length of the trail in miles, and $G$ is the altitude gain in feet. The model estimates that it will take $69$ minutes to hike to the top if a trail is $1.5$ miles long and ascends $800$ feet, as well as if a trail is $1.2$ miles long and ascends $1100$ feet. How many minutes does the model estimate it will take to hike to the top if the trail is $4.2$ miles long and ascends $4000$ feet? \n\n$\\textbf{(A) }240\\qquad\\textbf{(B) }246\\qquad\\textbf{(C) }252\\qquad\\textbf{(D) }258\\qquad\\textbf{(E) }264$", "ost_step": {}, "direct_answer": {"text": "Let's think step by step. Let $aL+bG$ be the function representing the estimated hiking time. The problem states that $69=T(a \\cdot 1.5+b \\cdot 800)=T(1.5a+800b)$ when the trail is 1.5 miles long and gains 800 feet in elevation, and $69=T(a \\cdot 1.2+b \\cdot 1100)=T(1.2a+1100b)$ when the trail is 1.2 miles long and gains 1100 feet in elevation. Subtracting these two equations eliminates T, giving $(1.5a+800b)-(1.2a+1100b)=-31b+0.3a=69$, which reduces to $31b/a=-(69/300)$. Substituting the values of a and b back into the original equation yields $T=(aL+bG)=(69/(-69/300)+1.2a)/L+(69/(31b/(-69/300)))$.$T=(3.6/300)(4.2)+4.8=0.0464*4.2+4.8=0.19548+4.8=4.99548.$The final answer is B. The answer is B.", "value": 0.25}}}, "rollout_id": 0}]